WeatherApp/WeatherAppGUI.py
WeatherApp/WeatherApp_DataExtraction.py
WeatherApp/WeatherApp_main.py
WeatherApp/__init__.py
WeatherApp/test_WeatherApp_DataExtraction.py
WeatherApp_pck-0.0.4.dist-info/METADATA
WeatherApp_pck-0.0.4.dist-info/WHEEL
WeatherApp_pck-0.0.4.dist-info/top_level.txt
WeatherApp_pck-0.0.4.dist-info/RECORD
