Metadata-Version: 2.1
Name: WeatherApp-pck
Version: 0.0.4
Summary: Package WeatherApp with whl
Author: Jan Osredkar
Author-email: jo6434@student.uni-lj.si
Classifier: Programming Language :: Python :: 3
Classifier: License :: OSI Approved :: MIT License
Classifier: Operating System :: OS Independent
Requires-Python: >=3.6
